cloudpack/__init__.py
cloudpack/__main__.py
cloudpack/cli.py
cloudpack/config.py
cloudpack/crypto.py
cloudpack/utils.py
cloudpack/vault.py
cloudpack-0.0.4.dist-info/licenses/LICENSE
cloudpack-0.0.4.dist-info/METADATA
cloudpack-0.0.4.dist-info/WHEEL
cloudpack-0.0.4.dist-info/entry_points.txt
cloudpack-0.0.4.dist-info/top_level.txt
cloudpack-0.0.4.dist-info/RECORD
