Metadata-Version: 2.4
Name: cloudpack
Version: 0.0.4
Summary: Multi-cloud file vault with end-to-end encryption and chunked storage.
Author: atar4xis
Requires-Python: >=3.10
License-File: LICENSE
Requires-Dist: cryptography
Requires-Dist: click
Dynamic: license-file
